{"nodes":[{"id":"route","label":"route.js","file_type":"code","source_file":"E:\\Project\\easylink-frontend\\app\\api\\attendance\\review\\route.js","source_location":"L1"},{"id":"route_hastable","label":"hasTable()","file_type":"code","source_file":"E:\\Project\\easylink-frontend\\app\\api\\attendance\\review\\route.js","source_location":"L19"},{"id":"route_tominutes","label":"toMinutes()","file_type":"code","source_file":"E:\\Project\\easylink-frontend\\app\\api\\attendance\\review\\route.js","source_location":"L34"},{"id":"route_buildstatus","label":"buildStatus()","file_type":"code","source_file":"E:\\Project\\easylink-frontend\\app\\api\\attendance\\review\\route.js","source_location":"L43"},{"id":"route_ensurereviewtagtable","label":"ensureReviewTagTable()","file_type":"code","source_file":"E:\\Project\\easylink-frontend\\app\\api\\attendance\\review\\route.js","source_location":"L63"},{"id":"route_ensurereviewmutationaudittable","label":"ensureReviewMutationAuditTable()","file_type":"code","source_file":"E:\\Project\\easylink-frontend\\app\\api\\attendance\\review\\route.js","source_location":"L80"},{"id":"route_appendreviewmutationaudit","label":"appendReviewMutationAudit()","file_type":"code","source_file":"E:\\Project\\easylink-frontend\\app\\api\\attendance\\review\\route.js","source_location":"L102"},{"id":"route_get","label":"GET()","file_type":"code","source_file":"E:\\Project\\easylink-frontend\\app\\api\\attendance\\review\\route.js","source_location":"L136"},{"id":"route_post","label":"POST()","file_type":"code","source_file":"E:\\Project\\easylink-frontend\\app\\api\\attendance\\review\\route.js","source_location":"L285"}],"edges":[{"source":"route","target":"server","relation":"imports_from","confidence":"EXTRACTED","source_file":"E:\\Project\\easylink-frontend\\app\\api\\attendance\\review\\route.js","source_location":"L3","weight":1},{"source":"route","target":"db","relation":"imports_from","confidence":"EXTRACTED","source_file":"E:\\Project\\easylink-frontend\\app\\api\\attendance\\review\\route.js","source_location":"L4","weight":1},{"source":"route","target":"karyawan_schema","relation":"imports_from","confidence":"EXTRACTED","source_file":"E:\\Project\\easylink-frontend\\app\\api\\attendance\\review\\route.js","source_location":"L5","weight":1},{"source":"route","target":"auth_session","relation":"imports_from","confidence":"EXTRACTED","source_file":"E:\\Project\\easylink-frontend\\app\\api\\attendance\\review\\route.js","source_location":"L6","weight":1},{"source":"route","target":"authorization_adapter","relation":"imports_from","confidence":"EXTRACTED","source_file":"E:\\Project\\easylink-frontend\\app\\api\\attendance\\review\\route.js","source_location":"L11","weight":1},{"source":"route","target":"route_hastable","relation":"contains","confidence":"EXTRACTED","source_file":"E:\\Project\\easylink-frontend\\app\\api\\attendance\\review\\route.js","source_location":"L19","weight":1},{"source":"route","target":"route_tominutes","relation":"contains","confidence":"EXTRACTED","source_file":"E:\\Project\\easylink-frontend\\app\\api\\attendance\\review\\route.js","source_location":"L34","weight":1},{"source":"route","target":"route_buildstatus","relation":"contains","confidence":"EXTRACTED","source_file":"E:\\Project\\easylink-frontend\\app\\api\\attendance\\review\\route.js","source_location":"L43","weight":1},{"source":"route","target":"route_ensurereviewtagtable","relation":"contains","confidence":"EXTRACTED","source_file":"E:\\Project\\easylink-frontend\\app\\api\\attendance\\review\\route.js","source_location":"L63","weight":1},{"source":"route","target":"route_ensurereviewmutationaudittable","relation":"contains","confidence":"EXTRACTED","source_file":"E:\\Project\\easylink-frontend\\app\\api\\attendance\\review\\route.js","source_location":"L80","weight":1},{"source":"route","target":"route_appendreviewmutationaudit","relation":"contains","confidence":"EXTRACTED","source_file":"E:\\Project\\easylink-frontend\\app\\api\\attendance\\review\\route.js","source_location":"L102","weight":1},{"source":"route","target":"route_get","relation":"contains","confidence":"EXTRACTED","source_file":"E:\\Project\\easylink-frontend\\app\\api\\attendance\\review\\route.js","source_location":"L136","weight":1},{"source":"route","target":"route_post","relation":"contains","confidence":"EXTRACTED","source_file":"E:\\Project\\easylink-frontend\\app\\api\\attendance\\review\\route.js","source_location":"L285","weight":1},{"source":"route_hastable","target":"route_get","relation":"calls","confidence":"EXTRACTED","source_file":"E:\\Project\\easylink-frontend\\app\\api\\attendance\\review\\route.js","source_location":"L20","weight":1},{"source":"route_buildstatus","target":"route_tominutes","relation":"calls","confidence":"EXTRACTED","source_file":"E:\\Project\\easylink-frontend\\app\\api\\attendance\\review\\route.js","source_location":"L45","weight":1},{"source":"route_appendreviewmutationaudit","target":"route_ensurereviewmutationaudittable","relation":"calls","confidence":"EXTRACTED","source_file":"E:\\Project\\easylink-frontend\\app\\api\\attendance\\review\\route.js","source_location":"L114","weight":1},{"source":"route_get","target":"route_hastable","relation":"calls","confidence":"EXTRACTED","source_file":"E:\\Project\\easylink-frontend\\app\\api\\attendance\\review\\route.js","source_location":"L145","weight":1},{"source":"route_post","target":"route_hastable","relation":"calls","confidence":"EXTRACTED","source_file":"E:\\Project\\easylink-frontend\\app\\api\\attendance\\review\\route.js","source_location":"L307","weight":1},{"source":"route_post","target":"route_appendreviewmutationaudit","relation":"calls","confidence":"EXTRACTED","source_file":"E:\\Project\\easylink-frontend\\app\\api\\attendance\\review\\route.js","source_location":"L327","weight":1},{"source":"route_post","target":"route_ensurereviewtagtable","relation":"calls","confidence":"EXTRACTED","source_file":"E:\\Project\\easylink-frontend\\app\\api\\attendance\\review\\route.js","source_location":"L384","weight":1}]}