{"nodes":[{"id":"page","label":"page.jsx","file_type":"code","source_file":"E:\\Project\\easylink-frontend\\app\\page.jsx","source_location":"L1"},{"id":"page_getstats","label":"getStats()","file_type":"code","source_file":"E:\\Project\\easylink-frontend\\app\\page.jsx","source_location":"L9"},{"id":"page_verifylabel","label":"verifyLabel()","file_type":"code","source_file":"E:\\Project\\easylink-frontend\\app\\page.jsx","source_location":"L158"},{"id":"page_normalizelimit","label":"normalizeLimit()","file_type":"code","source_file":"E:\\Project\\easylink-frontend\\app\\page.jsx","source_location":"L170"},{"id":"page_normalizepage","label":"normalizePage()","file_type":"code","source_file":"E:\\Project\\easylink-frontend\\app\\page.jsx","source_location":"L176"},{"id":"page_pagelink","label":"pageLink()","file_type":"code","source_file":"E:\\Project\\easylink-frontend\\app\\page.jsx","source_location":"L182"},{"id":"page_recentscankey","label":"recentScanKey()","file_type":"code","source_file":"E:\\Project\\easylink-frontend\\app\\page.jsx","source_location":"L186"},{"id":"page_dashboard","label":"Dashboard()","file_type":"code","source_file":"E:\\Project\\easylink-frontend\\app\\page.jsx","source_location":"L199"}],"edges":[{"source":"page","target":"link","relation":"imports_from","confidence":"EXTRACTED","source_file":"E:\\Project\\easylink-frontend\\app\\page.jsx","source_location":"L1","weight":1},{"source":"page","target":"navigation","relation":"imports_from","confidence":"EXTRACTED","source_file":"E:\\Project\\easylink-frontend\\app\\page.jsx","source_location":"L2","weight":1},{"source":"page","target":"lucide_react","relation":"imports_from","confidence":"EXTRACTED","source_file":"E:\\Project\\easylink-frontend\\app\\page.jsx","source_location":"L3","weight":1},{"source":"page","target":"db","relation":"imports_from","confidence":"EXTRACTED","source_file":"E:\\Project\\easylink-frontend\\app\\page.jsx","source_location":"L4","weight":1},{"source":"page","target":"karyawan_schema","relation":"imports_from","confidence":"EXTRACTED","source_file":"E:\\Project\\easylink-frontend\\app\\page.jsx","source_location":"L5","weight":1},{"source":"page","target":"auth_session","relation":"imports_from","confidence":"EXTRACTED","source_file":"E:\\Project\\easylink-frontend\\app\\page.jsx","source_location":"L6","weight":1},{"source":"page","target":"dashboard_ops_panel","relation":"imports_from","confidence":"EXTRACTED","source_file":"E:\\Project\\easylink-frontend\\app\\page.jsx","source_location":"L7","weight":1},{"source":"page","target":"page_getstats","relation":"contains","confidence":"EXTRACTED","source_file":"E:\\Project\\easylink-frontend\\app\\page.jsx","source_location":"L9","weight":1},{"source":"page","target":"page_verifylabel","relation":"contains","confidence":"EXTRACTED","source_file":"E:\\Project\\easylink-frontend\\app\\page.jsx","source_location":"L158","weight":1},{"source":"page","target":"page_normalizelimit","relation":"contains","confidence":"EXTRACTED","source_file":"E:\\Project\\easylink-frontend\\app\\page.jsx","source_location":"L170","weight":1},{"source":"page","target":"page_normalizepage","relation":"contains","confidence":"EXTRACTED","source_file":"E:\\Project\\easylink-frontend\\app\\page.jsx","source_location":"L176","weight":1},{"source":"page","target":"page_pagelink","relation":"contains","confidence":"EXTRACTED","source_file":"E:\\Project\\easylink-frontend\\app\\page.jsx","source_location":"L182","weight":1},{"source":"page","target":"page_recentscankey","relation":"contains","confidence":"EXTRACTED","source_file":"E:\\Project\\easylink-frontend\\app\\page.jsx","source_location":"L186","weight":1},{"source":"page","target":"page_dashboard","relation":"contains","confidence":"EXTRACTED","source_file":"E:\\Project\\easylink-frontend\\app\\page.jsx","source_location":"L199","weight":1},{"source":"page_dashboard","target":"page_normalizelimit","relation":"calls","confidence":"EXTRACTED","source_file":"E:\\Project\\easylink-frontend\\app\\page.jsx","source_location":"L204","weight":1},{"source":"page_dashboard","target":"page_normalizepage","relation":"calls","confidence":"EXTRACTED","source_file":"E:\\Project\\easylink-frontend\\app\\page.jsx","source_location":"L205","weight":1},{"source":"page_dashboard","target":"page_getstats","relation":"calls","confidence":"EXTRACTED","source_file":"E:\\Project\\easylink-frontend\\app\\page.jsx","source_location":"L206","weight":1},{"source":"page_dashboard","target":"page_pagelink","relation":"calls","confidence":"EXTRACTED","source_file":"E:\\Project\\easylink-frontend\\app\\page.jsx","source_location":"L440","weight":1}]}